{
  "count": 50,
  "items": [
    {
      "id": "Q01",
      "category": "투자 철학",
      "author": "워렌 버핏",
      "text": "첫째, 돈을 잃지 마라. 둘째, 첫 번째 원칙을 절대 잊지 마라."
    },
    {
      "id": "Q02",
      "category": "투자 철학",
      "author": "워렌 버핏",
      "text": "10년 동안 보유할 주식이 아니라면, 10분도 보유하지 마라."
    },
    {
      "id": "Q03",
      "category": "투자 철학",
      "author": "워렌 버핏",
      "text": "가격은 당신이 지불하는 것이고, 가치는 당신이 얻는 것이다."
    },
    {
      "id": "Q04",
      "category": "투자 철학",
      "author": "워렌 버핏",
      "text": "남들이 탐욕스러울 때 두려워하고, 남들이 두려워할 때 탐욕스러워라."
    },
    {
      "id": "Q05",
      "category": "투자 철학",
      "author": "벤저민 그레이엄",
      "text": "시장은 단기적으로는 투표기계지만, 장기적으로는 저울이다."
    },
    {
      "id": "Q06",
      "category": "투자 철학",
      "author": "벤저민 그레이엄",
      "text": "투자자의 가장 큰 적은 자기 자신이다."
    },
    {
      "id": "Q07",
      "category": "투자 철학",
      "author": "찰리 멍거",
      "text": "인생의 큰 교훈은 반드시 아는 것에 집중하라는 것이다."
    },
    {
      "id": "Q08",
      "category": "투자 철학",
      "author": "찰리 멍거",
      "text": "빨리 부자가 되려고 하지 마라. 천천히 부자가 되려고 해라."
    },
    {
      "id": "Q09",
      "category": "투자 철학",
      "author": "피터 린치",
      "text": "당신이 이해하는 것에만 투자하라."
    },
    {
      "id": "Q10",
      "category": "투자 철학",
      "author": "피터 린치",
      "text": "주가는 결국 기업의 이익을 따라간다."
    },
    {
      "id": "Q11",
      "category": "시장 격언",
      "author": "존 템플턴",
      "text": "강세장은 비관 속에서 태어나, 회의 속에서 자라고, 낙관 속에서 성숙하며, 도취 속에서 죽는다."
    },
    {
      "id": "Q12",
      "category": "시장 격언",
      "author": "앙드레 코스톨라니",
      "text": "주식 시장에서 번 돈은 고통의 대가로 지불받는 돈이다. 먼저 고통이 오고, 그다음 돈이 온다."
    },
    {
      "id": "Q13",
      "category": "시장 격언",
      "author": "제시 리버모어",
      "text": "시장은 항상 옳다. 틀린 것은 언제나 나다."
    },
    {
      "id": "Q14",
      "category": "시장 격언",
      "author": "조지 소로스",
      "text": "중요한 것은 당신이 맞았는지 틀렸는지가 아니라, 맞았을 때 얼마를 벌고 틀렸을 때 얼마를 잃는가이다."
    },
    {
      "id": "Q15",
      "category": "시장 격언",
      "author": "필립 피셔",
      "text": "시장은 당신의 감정을 시험하는 곳이지, 증명하는 곳이 아니다."
    },
    {
      "id": "Q16",
      "category": "시장 격언",
      "author": "전래 격언",
      "text": "소문에 사서 뉴스에 팔아라."
    },
    {
      "id": "Q17",
      "category": "시장 격언",
      "author": "전래 격언",
      "text": "떨어지는 칼날은 잡지 마라."
    },
    {
      "id": "Q18",
      "category": "시장 격언",
      "author": "전래 격언",
      "text": "달걀을 한 바구니에 담지 마라."
    },
    {
      "id": "Q19",
      "category": "시장 격언",
      "author": "제시 리버모어",
      "text": "큰돈은 거래에서 오지 않는다. 기다림에서 온다."
    },
    {
      "id": "Q20",
      "category": "시장 격언",
      "author": "하워드 막스",
      "text": "이번엔 다르다는 말이 투자에서 가장 비싼 네 글자다."
    },
    {
      "id": "Q21",
      "category": "저축과 절약",
      "author": "벤저민 프랭클린",
      "text": "한 푼 아끼는 것은 한 푼 버는 것이다."
    },
    {
      "id": "Q22",
      "category": "저축과 절약",
      "author": "벤저민 프랭클린",
      "text": "작은 지출을 경계하라. 작은 구멍이 큰 배를 가라앉힌다."
    },
    {
      "id": "Q23",
      "category": "저축과 절약",
      "author": "존 보글",
      "text": "비용은 확실한 수익의 적이다. 줄일 수 있는 것부터 줄여라."
    },
    {
      "id": "Q24",
      "category": "저축과 절약",
      "author": "데이브 램지",
      "text": "오늘 남들이 안 하는 일을 하면, 내일 남들이 못 가진 것을 가질 수 있다."
    },
    {
      "id": "Q25",
      "category": "저축과 절약",
      "author": "토마스 J. 스탠리",
      "text": "부자는 돈을 많이 벌어서가 아니라, 적게 써서 부자가 된다."
    },
    {
      "id": "Q26",
      "category": "저축과 절약",
      "author": "워렌 버핏",
      "text": "쓰고 남은 돈을 저축하지 마라. 저축하고 남은 돈을 써라."
    },
    {
      "id": "Q27",
      "category": "저축과 절약",
      "author": "로버트 기요사키",
      "text": "가난한 사람은 비싼 것을 사고, 중산층은 부채를 사고, 부자는 자산을 산다."
    },
    {
      "id": "Q28",
      "category": "저축과 절약",
      "author": "조지 S. 클래이슨",
      "text": "당신이 버는 돈의 10분의 1은 반드시 당신의 것이어야 한다."
    },
    {
      "id": "Q29",
      "category": "마인드셋",
      "author": "나폴레온 힐",
      "text": "생각이 곧 현실이 된다. 부자의 사고방식을 먼저 가져라."
    },
    {
      "id": "Q30",
      "category": "마인드셋",
      "author": "레이 달리오",
      "text": "고통 + 성찰 = 발전. 이 방정식을 잊지 마라."
    },
    {
      "id": "Q31",
      "category": "마인드셋",
      "author": "나심 탈레브",
      "text": "견고함이 아니라, 깨지지 않는 것이 아니라, 역경에서 더 강해지는 것을 목표로 하라."
    },
    {
      "id": "Q32",
      "category": "마인드셋",
      "author": "제프 베조스",
      "text": "단기적으로 생각하는 사람이 99%다. 장기적으로만 생각해도 경쟁자가 사라진다."
    },
    {
      "id": "Q33",
      "category": "마인드셋",
      "author": "찰리 멍거",
      "text": "합리적이 되는 것이 천재가 되는 것보다 낫다."
    },
    {
      "id": "Q34",
      "category": "마인드셋",
      "author": "세네카",
      "text": "운이란 준비가 기회를 만났을 때 일어나는 일이다."
    },
    {
      "id": "Q35",
      "category": "마인드셋",
      "author": "짐 론",
      "text": "당신의 수입은 당신이 평소에 가장 많이 어울리는 다섯 사람의 평균이다."
    },
    {
      "id": "Q36",
      "category": "리스크 관리",
      "author": "하워드 막스",
      "text": "리스크는 변동성이 아니다. 리스크는 영구적인 손실의 가능성이다."
    },
    {
      "id": "Q37",
      "category": "리스크 관리",
      "author": "나심 탈레브",
      "text": "예측할 수 없는 것을 예측하려 하지 말고, 예측할 수 없는 일에 대비하라."
    },
    {
      "id": "Q38",
      "category": "리스크 관리",
      "author": "세스 클라만",
      "text": "안전마진이 없는 투자는 투기다."
    },
    {
      "id": "Q39",
      "category": "리스크 관리",
      "author": "레이 달리오",
      "text": "최악의 시나리오를 대비하지 않으면, 최악의 시나리오가 당신을 대비한다."
    },
    {
      "id": "Q40",
      "category": "리스크 관리",
      "author": "워렌 버핏",
      "text": "리스크는 자신이 무엇을 하고 있는지 모를 때 생긴다."
    },
    {
      "id": "Q41",
      "category": "복리와 시간",
      "author": "아인슈타인",
      "text": "복리는 세계 8번째 불가사의다. 이해하는 자는 벌고, 이해하지 못하는 자는 지불한다."
    },
    {
      "id": "Q42",
      "category": "복리와 시간",
      "author": "워렌 버핏",
      "text": "오늘 누군가 나무 그늘에 앉아 있는 이유는, 오래전에 누군가 나무를 심었기 때문이다."
    },
    {
      "id": "Q43",
      "category": "복리와 시간",
      "author": "찰리 멍거",
      "text": "복리의 첫 번째 규칙: 절대로 불필요하게 중단하지 마라."
    },
    {
      "id": "Q44",
      "category": "복리와 시간",
      "author": "모간 하우절",
      "text": "시간은 투자자의 가장 큰 레버리지다."
    },
    {
      "id": "Q45",
      "category": "복리와 시간",
      "author": "존 보글",
      "text": "시장을 이기려 하지 말고, 시장에 머물러 있어라."
    },
    {
      "id": "Q46",
      "category": "한국 투자자",
      "author": "존 리",
      "text": "월급쟁이도 주주가 될 수 있다. 소비자에서 주주로 포지션을 바꿔라."
    },
    {
      "id": "Q47",
      "category": "한국 투자자",
      "author": "존 리",
      "text": "사교육비를 줄여 그 돈으로 자녀 이름의 주식을 사주어라."
    },
    {
      "id": "Q48",
      "category": "한국 투자자",
      "author": "김승호",
      "text": "돈은 인격체다. 함부로 대하면 떠나고, 귀하게 여기면 모인다."
    },
    {
      "id": "Q49",
      "category": "한국 투자자",
      "author": "박경철",
      "text": "경제적 자유는 돈의 크기가 아니라, 선택의 크기다."
    },
    {
      "id": "Q50",
      "category": "한국 투자자",
      "author": "강방천",
      "text": "주식 투자는 사업의 동업이다. 주주가 아닌 트레이더가 되지 마라."
    }
  ]
}
